Metadata-Version: 2.1
Name: graphene-file-upload-patch
Version: 1.3.0.0
Summary: Lib for adding file upload functionality to GraphQL mutations in Graphene Django and Flask-Graphql
Home-page: https://github.com/gabrielsebag/graphene-file-upload
Author: Gabriel Sebag
Author-email: hello@gabrielsebag.com
Keywords: graphql,graphene,apollo,upload
Classifier: Development Status :: 5 - Production/Stable
Classifier: Intended Audience :: Developers
Classifier: License :: OSI Approved :: MIT License
Classifier: Natural Language :: English
Classifier: Topic :: Internet :: WWW/HTTP
Classifier: Operating System :: OS Independent
Classifier: Programming Language :: Python :: 2.7
Classifier: Programming Language :: Python :: 3.4
Classifier: Programming Language :: Python :: 3.5
Classifier: Programming Language :: Python :: 3.6
Classifier: Programming Language :: Python :: 3.7
Classifier: Programming Language :: Python :: 3.8
Classifier: Programming Language :: Python :: 3.9
Classifier: Programming Language :: Python :: Implementation :: CPython
Classifier: Programming Language :: Python :: Implementation :: PyPy
Classifier: Framework :: Django :: 1.11
Classifier: Framework :: Django :: 2.0
Classifier: Framework :: Django :: 2.1
Classifier: Framework :: Django :: 2.2
Classifier: Framework :: Django :: 3.0
Classifier: Framework :: Django :: 3.1
Classifier: Framework :: Django :: 3.2
Classifier: Framework :: Flask
Provides-Extra: flask
Provides-Extra: django
Provides-Extra: all
Provides-Extra: tests
License-File: LICENSE
